{
  "items": [
    {
      "type": "file",
      "ctime": 1681343611460,
      "path": "Atlas/Shares/Videos/Obsidian Bookmarks (video).md"
    },
    {
      "type": "file",
      "ctime": 1737472416480,
      "path": "1 - Rough Notes/Sleep time notes.md",
      "title": "Sleep Time Notes"
    },
    {
      "type": "file",
      "ctime": 1739253001170,
      "path": "1 - notes/z. others/vault-status.md",
      "title": "Vault Status"
    },
    {
      "type": "file",
      "ctime": 1741006682424,
      "path": "1 - notes/z. others/videos to watch eventually.md",
      "title": "watch it bro"
    },
    {
      "type": "file",
      "ctime": 1741006757096,
      "path": "1 - notes/z. others/Youtubers for programming.md",
      "title": "ytbers"
    },
    {
      "type": "file",
      "ctime": 1743155425646,
      "path": "1 - notes/z. others/Tasks for coding.md",
      "title": "Tasks"
    },
    {
      "type": "group",
      "ctime": 1743964777784,
      "items": [
        {
          "type": "file",
          "ctime": 1743964989910,
          "path": "1 - notes/z. others/Websites and Resources.md",
          "title": "website list"
        },
        {
          "type": "file",
          "ctime": 1743964805472,
          "path": "1 - notes/z. others/Questions asked in interview.md",
          "title": "Interview Questions"
        },
        {
          "type": "file",
          "ctime": 1740576809756,
          "path": "1 - notes/a. concepts/core/DSA Approaches.md",
          "title": "DSA"
        }
      ],
      "title": "Most IMP"
    },
    {
      "type": "file",
      "ctime": 1745123449147,
      "path": "1 - notes/z. others/roadmap.md",
      "title": "RoadMap"
    },
    {
      "type": "file",
      "ctime": 1747335103002,
      "path": "3 - moc/MOC-LIST.md",
      "title": "moc's list"
    },
    {
      "type": "file",
      "ctime": 1748440152061,
      "path": "0 - inbox/code for js moc.md",
      "title": "code block"
    },
    {
      "type": "file",
      "ctime": 1748440169880,
      "path": "1 - notes/z. others/code copy block note.md",
      "title": "code block"
    }
  ]
}