{
  "main": {
    "id": "c4f7fdb608baf8e1",
    "type": "split",
    "children": [
      {
        "id": "3d20ac3963eb32b5",
        "type": "tabs",
        "children": [
          {
            "id": "5545960ace0cab2c",
            "type": "leaf",
            "pane-relief:history-v1": {
              "pos": 0,
              "stack": [
                {
                  "state": "{}",
                  "eState": "{}"
                },
                {
                  "title": "github remote",
                  "icon": "lucide-file",
                  "state": "{\"type\":\"markdown\",\"state\":{\"file\":\"1 - notes/c. tools/github/github remote.md\",\"mode\":\"source\",\"source\":false,\"backlinks\":true,\"backlinkOpts\":{\"collapseAll\":false,\"extraContext\":false,\"sortOrder\":\"alphabetical\",\"showSearch\":false,\"searchQuery\":\"\",\"backlinkCollapsed\":false,\"unlinkedCollapsed\":true}},\"icon\":\"lucide-file\",\"title\":\"github remote\"}",
                  "eState": "{\"cursor\":{\"from\":{\"line\":7,\"ch\":0},\"to\":{\"line\":7,\"ch\":0}},\"scroll\":0}"
                },
                {
                  "title": "redux intro",
                  "icon": "lucide-file",
                  "state": "{\"type\":\"markdown\",\"state\":{\"file\":\"1 - notes/h. modules/react/redux intro.md\",\"mode\":\"source\",\"source\":false,\"backlinks\":true,\"backlinkOpts\":{\"collapseAll\":false,\"extraContext\":false,\"sortOrder\":\"alphabetical\",\"showSearch\":false,\"searchQuery\":\"\",\"backlinkCollapsed\":false,\"unlinkedCollapsed\":true}},\"icon\":\"lucide-file\",\"title\":\"redux intro\"}",
                  "eState": "{\"cursor\":{\"from\":{\"line\":33,\"ch\":0},\"to\":{\"line\":33,\"ch\":0}},\"scroll\":22.349359480160814}"
                },
                {
                  "title": "redux",
                  "icon": "lucide-file",
                  "state": "{\"type\":\"markdown\",\"state\":{\"file\":\"1 - notes/h. modules/react/redux.md\",\"mode\":\"source\",\"source\":false,\"backlinks\":true,\"backlinkOpts\":{\"collapseAll\":false,\"extraContext\":false,\"sortOrder\":\"alphabetical\",\"showSearch\":false,\"searchQuery\":\"\",\"backlinkCollapsed\":false,\"unlinkedCollapsed\":true}},\"icon\":\"lucide-file\",\"title\":\"redux\"}",
                  "eState": "{\"cursor\":{\"from\":{\"line\":8,\"ch\":11},\"to\":{\"line\":8,\"ch\":11}},\"scroll\":0}"
                },
                {
                  "title": "React-MOC",
                  "icon": "lucide-file",
                  "state": "{\"type\":\"markdown\",\"state\":{\"file\":\"3 - moc/sub-mocs/React-MOC.md\",\"mode\":\"source\",\"source\":false,\"backlinks\":true,\"backlinkOpts\":{\"collapseAll\":false,\"extraContext\":false,\"sortOrder\":\"alphabetical\",\"showSearch\":false,\"searchQuery\":\"\",\"backlinkCollapsed\":false,\"unlinkedCollapsed\":true}},\"icon\":\"lucide-file\",\"title\":\"React-MOC\"}",
                  "eState": "{\"cursor\":{\"from\":{\"line\":30,\"ch\":0},\"to\":{\"line\":30,\"ch\":0}},\"scroll\":18.008012779211327}"
                }
              ]
            },
            "state": {
              "type": "markdown",
              "state": {
                "file": "3 - moc/sub-mocs/git-and-github-MOC.md",
                "mode": "source",
                "source": false,
                "backlinks": true,
                "backlinkOpts": {
                  "collapseAll": false,
                  "extraContext": false,
                  "sortOrder": "alphabetical",
                  "showSearch": false,
                  "searchQuery": "",
                  "backlinkCollapsed": false,
                  "unlinkedCollapsed": true
                }
              },
              "icon": "lucide-file",
              "title": "git-and-github-MOC"
            }
          }
        ]
      }
    ],
    "direction": "vertical"
  },
  "left": {
    "id": "440b3841429709ed",
    "type": "split",
    "children": [
      {
        "id": "b208c03cadd231ee",
        "type": "tabs",
        "dimension": 76.60818713450293,
        "children": [
          {
            "id": "dddbab8b18fd423a",
            "type": "leaf",
            "pane-relief:history-v1": {
              "pos": 0,
              "stack": [
                {
                  "state": "{}",
                  "eState": "{}"
                }
              ]
            },
            "state": {
              "type": "file-explorer",
              "state": {
                "sortOrder": "alphabetical",
                "autoReveal": false
              },
              "icon": "lucide-folder-closed",
              "title": "Files"
            }
          },
          {
            "id": "77966b04a7f238ed",
            "type": "leaf",
            "pane-relief:history-v1": {
              "pos": 0,
              "stack": [
                {
                  "state": "{}",
                  "eState": "{}"
                }
              ]
            },
            "state": {
              "type": "search",
              "state": {
                "query": "",
                "matchingCase": false,
                "explainSearch": false,
                "collapseAll": false,
                "extraContext": false,
                "sortOrder": "alphabetical"
              },
              "icon": "lucide-search",
              "title": "Search"
            }
          },
          {
            "id": "610c153585bceb88",
            "type": "leaf",
            "pane-relief:history-v1": {
              "pos": 0,
              "stack": [
                {
                  "state": "{}",
                  "eState": "{}"
                }
              ]
            },
            "state": {
              "type": "bookmarks",
              "state": {},
              "icon": "lucide-bookmark",
              "title": "Bookmarks"
            }
          }
        ]
      },
      {
        "id": "3888432cac3b4f06",
        "type": "tabs",
        "dimension": 23.391812865497073,
        "children": [
          {
            "id": "727ed8f5dbac01b5",
            "type": "leaf",
            "pane-relief:history-v1": {
              "pos": 0,
              "stack": [
                {
                  "state": "{}",
                  "eState": "{}"
                }
              ]
            },
            "state": {
              "type": "localgraph",
              "state": {
                "file": "3 - moc/sub-mocs/git-and-github-MOC.md",
                "options": {
                  "collapse-filter": false,
                  "search": "",
                  "localJumps": 1,
                  "localBacklinks": true,
                  "localForelinks": true,
                  "localInterlinks": true,
                  "showTags": false,
                  "showAttachments": false,
                  "hideUnresolved": false,
                  "collapse-color-groups": true,
                  "colorGroups": [],
                  "collapse-display": false,
                  "showArrow": true,
                  "textFadeMultiplier": 0,
                  "nodeSizeMultiplier": 1,
                  "lineSizeMultiplier": 1,
                  "collapse-forces": true,
                  "centerStrength": 0.518713248970312,
                  "repelStrength": 10,
                  "linkStrength": 1,
                  "linkDistance": 250,
                  "scale": 0.3628873693012117,
                  "close": true
                }
              },
              "icon": "lucide-git-fork",
              "title": "Graph of git-and-github-MOC"
            }
          }
        ]
      }
    ],
    "direction": "horizontal",
    "width": 279.5
  },
  "right": {
    "id": "7a43a6c530e72e44",
    "type": "split",
    "children": [
      {
        "id": "ea89fdbc5439f479",
        "type": "tabs",
        "dimension": 61.165048543689316,
        "children": [
          {
            "id": "90d026528dc7103b",
            "type": "leaf",
            "pane-relief:history-v1": {
              "pos": 0,
              "stack": [
                {
                  "state": "{}",
                  "eState": "{}"
                }
              ]
            },
            "state": {
              "type": "outline",
              "state": {
                "file": "1 - notes/h. modules/bcrypt hash and verification.md",
                "followCursor": false,
                "showSearch": false,
                "searchQuery": ""
              },
              "icon": "lucide-list",
              "title": "Outline of bcrypt hash and verification"
            }
          },
          {
            "id": "4f6e4ddebde66a86",
            "type": "leaf",
            "pane-relief:history-v1": {
              "pos": 0,
              "stack": [
                {
                  "state": "{}",
                  "eState": "{}"
                }
              ]
            },
            "state": {
              "type": "tag",
              "state": {
                "sortOrder": "alphabetical",
                "useHierarchy": true,
                "showSearch": false,
                "searchQuery": ""
              },
              "icon": "lucide-tags",
              "title": "Tags"
            }
          },
          {
            "id": "2834b0489acc80da",
            "type": "leaf",
            "pane-relief:history-v1": {
              "pos": 0,
              "stack": [
                {
                  "state": "{}",
                  "eState": "{}"
                }
              ]
            },
            "state": {
              "type": "all-properties",
              "state": {
                "sortOrder": "frequency",
                "showSearch": true,
                "searchQuery": ""
              },
              "icon": "lucide-archive",
              "title": "All properties"
            }
          },
          {
            "id": "7c9608917441ba5b",
            "type": "leaf",
            "pane-relief:history-v1": {
              "pos": 0,
              "stack": [
                {
                  "state": "{}",
                  "eState": "{}"
                }
              ]
            },
            "state": {
              "type": "advanced-tables-toolbar",
              "state": {},
              "icon": "spreadsheet",
              "title": "Advanced Tables"
            }
          },
          {
            "id": "8972c7b786ae0918",
            "type": "leaf",
            "pane-relief:history-v1": {
              "pos": 0,
              "stack": [
                {
                  "state": "{}",
                  "eState": "{}"
                }
              ]
            },
            "state": {
              "type": "Strange New Worlds",
              "state": {},
              "icon": "file-digit",
              "title": "Strange New Worlds"
            }
          },
          {
            "id": "bac75d968ea47341",
            "type": "leaf",
            "pane-relief:history-v1": {
              "pos": 0,
              "stack": [
                {
                  "state": "{}",
                  "eState": "{}"
                }
              ]
            },
            "state": {
              "type": "todo",
              "state": {},
              "icon": "checkmark",
              "title": "Todo List"
            }
          },
          {
            "id": "bfc172420fbe95f9",
            "type": "leaf",
            "pane-relief:history-v1": {
              "pos": 0,
              "stack": [
                {
                  "state": "{}",
                  "eState": "{}"
                }
              ]
            },
            "state": {
              "type": "Strange New Worlds",
              "state": {},
              "icon": "file-digit",
              "title": "Strange New Worlds"
            }
          },
          {
            "id": "42d5e05e46b95bc2",
            "type": "leaf",
            "pane-relief:history-v1": {
              "pos": 0,
              "stack": [
                {
                  "state": "{}",
                  "eState": "{}"
                }
              ]
            },
            "state": {
              "type": "git-view",
              "state": {},
              "icon": "git-pull-request",
              "title": "Source Control"
            }
          }
        ],
        "currentTab": 7
      },
      {
        "id": "8e15cd93a6a4be64",
        "type": "tabs",
        "dimension": 38.834951456310684,
        "children": [
          {
            "id": "d535bd36dbc98e0b",
            "type": "leaf",
            "pane-relief:history-v1": {
              "pos": 0,
              "stack": [
                {
                  "state": "{}",
                  "eState": "{}"
                }
              ]
            },
            "state": {
              "type": "backlink",
              "state": {
                "file": "3 - moc/sub-mocs/git-and-github-MOC.md",
                "collapseAll": false,
                "extraContext": false,
                "sortOrder": "alphabetical",
                "showSearch": false,
                "searchQuery": "",
                "backlinkCollapsed": false,
                "unlinkedCollapsed": false
              },
              "icon": "links-coming-in",
              "title": "Backlinks for git-and-github-MOC"
            }
          },
          {
            "id": "ae0aed29d208c352",
            "type": "leaf",
            "pane-relief:history-v1": {
              "pos": 0,
              "stack": [
                {
                  "state": "{}",
                  "eState": "{}"
                }
              ]
            },
            "state": {
              "type": "outgoing-link",
              "state": {
                "file": "Calendar/2024/Week 43/2024-10-21.md",
                "linksCollapsed": false,
                "unlinkedCollapsed": true
              },
              "icon": "links-going-out",
              "title": "Outgoing links from 2024-10-21"
            }
          }
        ]
      }
    ],
    "direction": "horizontal",
    "width": 438.5
  },
  "left-ribbon": {
    "hiddenItems": {
      "bases:Create new base": false,
      "audio-recorder:Start/stop recording": false,
      "graph:Open graph view": false,
      "publish:Publish changes...": false,
      "switcher:Open quick switcher": false,
      "command-palette:Open command palette": false,
      "templates:Insert template": false,
      "canvas:Create new canvas": false,
      "workspaces:Manage workspace layouts": false,
      "darlal-switcher-plus:Open in Headings Mode": false,
      "darlal-switcher-plus:Open Symbols for the active editor": false,
      "callout-manager:Insert Callout": false,
      "templater-obsidian:Templater": false,
      "obsidian-git:Open Git source control": false
    }
  },
  "active": "5545960ace0cab2c",
  "lastOpenFiles": [
    "1 - notes/c. tools/github/github remote.md",
    "1 - notes/h. modules/react/redux intro.md",
    "1 - notes/h. modules/react/redux.md",
    "3 - moc/sub-mocs/React-MOC.md",
    "1 - notes/h. modules/react/react - about.md",
    "1 - notes/h. modules/react/react story + W's.md",
    "1 - notes/h. modules/react/react topics to learn.md",
    "1 - notes/h. modules/react/react - things to remember.md",
    "1 - notes/h. modules/react/React Cheatsheet.md",
    "0 - inbox/ai basics.md",
    "3 - moc/AI-ML-MOC.md",
    "3 - moc/sub-mocs/Java-MOC.md",
    "3 - moc/Lang-And-Packages-MOC.md",
    "1 - notes/h. modules/bcrypt hash and verification.md",
    "3 - moc/sub-mocs/Python-MOC.md",
    "3 - moc/sub-mocs/git-and-github-MOC.md",
    "1 - notes/b. languages/java/java basics.md",
    "1 - notes/b. languages/java/java boiler plate.md",
    "0 - inbox/how python works.md",
    "1 - notes/b. languages/java/java multithreading.md",
    "1 - notes/e. ai/terms for AI.md",
    "4 - sources/courses/n8n course by sheriyas.md",
    "4 - sources/courses/ChaiAurCode SQL course.md",
    "1 - notes/a. concepts/datatype.md",
    "0 - inbox/guide on how to deploy apps.md",
    "98 - attachments/Pasted image 20250819134250.png",
    "1 - notes/h. modules/bcrypt salt.md",
    "98 - attachments/Screenshot_2024-10-06_at_7.44.33_PM.webp",
    "1 - notes/b. languages/sql",
    "1 - notes/x. code block",
    "98 - attachments/screen-shot-2023-10-27-at-5.57.55-pm.jpeg",
    "98 - attachments/screen-shot-2024-01-18-at-3.58.27-pm.jpeg",
    "98 - attachments/screen-shot-2023-10-27-at-5.55.07-pm.jpeg",
    "98 - attachments/screenshot-2025-02-21-at-3.48.23pm.jpeg",
    "98 - attachments/Pasted image 20250601140028.png",
    "98 - attachments/Pasted image 20250705120119.png",
    "98 - attachments/Pasted image 20250705120059.png",
    "98 - attachments/Pasted image 20250627115455.png",
    "4 - sources/courses/dbms by code help",
    "1 - notes/y. snippets",
    "98 - attachments/Recording 20250626175237.m4a",
    "98 - attachments/Recording 20250616183328.m4a",
    "98 - attachments/Recording 20250616183748.m4a",
    "98 - attachments/Recording 20250616183216.m4a",
    "98 - attachments/Recording 20250616182855.m4a",
    "98 - attachments/Recording 20250616183006.m4a",
    "Untitled.canvas",
    "Life Canvas.canvas",
    "Untitled 1.canvas",
    "Untitled 2.canvas",
    "Atlas/Utilities/Canvases/2023-03-20 - Review, Brain Dump, Imagine, Prioritize.canvas",
    "Atlas/Utilities/Canvases/LYT W10 Calendar Canvas.canvas",
    "Atlas/Utilities/Canvases/LYT Ship Dashboard.canvas",
    "Atlas/Utilities/Canvases/LYT W11 Calendar Canvas.canvas",
    "Atlas/Utilities/Canvases/Obsidian Canvas MOC.canvas",
    "Atlas/Utilities/Canvases/Ship of the Sensemaker.canvas"
  ]
}